blqs_cirq/__init__.py
blqs_cirq/_version.py
blqs_cirq/build.py
blqs_cirq/build_test.py
blqs_cirq/cirq_blqs_op.py
blqs_cirq/cirq_blqs_op_test.py
blqs_cirq/gates.py
blqs_cirq/gates_test.py
blqs_cirq/insert_strategy.py
blqs_cirq/insert_strategy_test.py
blqs_cirq/moment.py
blqs_cirq/moment_test.py
blqs_cirq/protocols.py
blqs_cirq/protocols_test.py
blqs_cirq/qubits.py
blqs_cirq/qubits_test.py
blqs_cirq/repeat.py
blqs_cirq/repeat_test.py
blqs_cirq/contrib/__init__.py
blqs_cirq/contrib/acquaintance/__init__.py
blqs_cirq/contrib/acquaintance/acquaintance_gates.py
blqs_cirq/contrib/acquaintance/acquaintance_gates_test.py
blqs_cirq/google/__init__.py
blqs_cirq/google/google_gates.py
blqs_cirq/google/google_gates_test.py
blqs_cirq/google/experimental/__init__.py
blqs_cirq/google/experimental/experimental_gates.py
blqs_cirq/google/experimental/experimental_gates_test.py
blqs_cirq-0.1.0.dist-info/METADATA
blqs_cirq-0.1.0.dist-info/WHEEL
blqs_cirq-0.1.0.dist-info/top_level.txt
blqs_cirq-0.1.0.dist-info/RECORD
