Metadata-Version: 2.1
Name: blqs-cirq
Version: 0.1.0
Summary: A library for writing imperative quantum computing programs in Cirq.
Home-page: https://github.com/ionq/blqs_cirq
Author: The Blqs Developers
Author-email: dabacon@gmail.com
License: Apache 2
Platform: UNKNOWN
Requires-Python: >=3.7.0
Requires-Dist: blqs
Requires-Dist: cirq-google (==0.13.1)
Requires-Dist: cirq (==0.13.1)
